android/__init__.py
android/adb_utils.py
android/app_utils.py
android/logcat_utils.py
android/performance_utils.py
database/__init__.py
database/db_utils.py
date/__init__.py
date/date_utils.py
decorator/__init__.py
decorator/decorator_utils.py
file/__init__.py
file/file_utils.py
log/__init__.py
log/log_utils.py
network/__init__.py
network/http_utils.py
system/__init__.py
system/system_utils.py
tests/__init__.py
tests/test_android_adb_utils.py
tests/test_android_adb_utils_advanced.py
tests/test_android_adb_utils_extended.py
tests/test_file_utils.py
pptools-0.1.0.dist-info/LICENSE
pptools-0.1.0.dist-info/METADATA
pptools-0.1.0.dist-info/WHEEL
pptools-0.1.0.dist-info/top_level.txt
pptools-0.1.0.dist-info/RECORD
