Metadata-Version: 2.2
Name: pptools
Version: 0.1.0
Summary: 一个全面的Python工具包，用于自动化测试和日常开发工作
Home-page: https://gitee.com/dyliujun/pptools.git
Author: PPTools Contributors
Author-email: your.email@example.com
Classifier: Programming Language :: Python :: 3
Classifier: License :: OSI Approved :: MIT License
Classifier: Operating System :: OS Independent
Classifier: Development Status :: 4 - Beta
Classifier: Intended Audience :: Developers
Classifier: Intended Audience :: Information Technology
Classifier: Topic :: Software Development :: Testing
Classifier: Topic :: Software Development :: Libraries :: Python Modules
Classifier: Topic :: Utilities
Requires-Python: >=3.6
License-File: LICENSE
Requires-Dist: requests
Requires-Dist: pyyaml
Requires-Dist: openpyxl
Requires-Dist: pymongo
Requires-Dist: redis
Requires-Dist: pandas
Requires-Dist: adbutils
Requires-Dist: psutil
Provides-Extra: database
Requires-Dist: pymongo; extra == "database"
Requires-Dist: pymysql; extra == "database"
Requires-Dist: redis; extra == "database"
Provides-Extra: dev
Requires-Dist: pytest; extra == "dev"
Requires-Dist: black; extra == "dev"
Requires-Dist: isort; extra == "dev"
Requires-Dist: mypy; extra == "dev"
Requires-Dist: flake8; extra == "dev"
Requires-Dist: build; extra == "dev"
Requires-Dist: twine; extra == "dev"
Dynamic: author
Dynamic: author-email
Dynamic: classifier
Dynamic: description
Dynamic: description-content-type
Dynamic: home-page
Dynamic: provides-extra
Dynamic: requires-dist
Dynamic: requires-python
Dynamic: summary
